{
  "$schema": "https://developer.microsoft.com/json-schemas/fabric/item/report/definition/visualContainer/2.3.0/schema.json",
  "name": "8a2ceec17b502000b18b",
  "position": {
    "x": 197.38410172952044,
    "y": 59.261369427230477,
    "z": 625,
    "height": 31.60606369452292,
    "width": 119.60471788332795,
    "tabOrder": 5000
  },
  "visual": {
    "visualType": "card",
    "query": {
      "queryState": {
        "Values": {
          "projections": [
            {
              "field": {
                "Measure": {
                  "Expression": {
                    "SourceRef": {
                      "Entity": "KPI"
                    }
                  },
                  "Property": "KPI+TXT Nb SR"
                }
              },
              "queryRef": "KPI.KPI+TXT Nb SR",
              "nativeQueryRef": "KPI+TXT Nb SR"
            }
          ]
        }
      },
      "sortDefinition": {
        "sort": [
          {
            "field": {
              "Measure": {
                "Expression": {
                  "SourceRef": {
                    "Entity": "KPI"
                  }
                },
                "Property": "Nb SR opened (Last mature point)"
              }
            },
            "direction": "Descending"
          }
        ],
        "isDefaultSort": true
      }
    },
    "objects": {
      "categoryLabels": [
        {
          "properties": {
            "show": {
              "expr": {
                "Literal": {
                  "Value": "false"
                }
              }
            }
          }
        }
      ],
      "labels": [
        {
          "properties": {
            "fontSize": {
              "expr": {
                "Literal": {
                  "Value": "14D"
                }
              }
            }
          }
        }
      ]
    },
    "visualContainerObjects": {
      "visualHeader": [
        {
          "properties": {
            "show": {
              "expr": {
                "Literal": {
                  "Value": "false"
                }
              }
            }
          }
        }
      ],
      "dropShadow": [
        {
          "properties": {
            "show": {
              "expr": {
                "Literal": {
                  "Value": "false"
                }
              }
            },
            "color": {
              "solid": {
                "color": {
                  "expr": {
                    "Literal": {
                      "Value": "'#D9CC3C'"
                    }
                  }
                }
              }
            }
          }
        }
      ],
      "title": [
        {
          "properties": {
            "text": {
              "expr": {
                "Literal": {
                  "Value": "'KPI nb SR MHDV Service BEV'"
                }
              }
            }
          }
        }
      ],
      "background": [
        {
          "properties": {
            "show": {
              "expr": {
                "Literal": {
                  "Value": "false"
                }
              }
            }
          }
        }
      ]
    },
    "drillFilterOtherVisuals": true
  },
  "parentGroupName": "6c39ba2db4536d6c2831",
  "filterConfig": {
    "filters": [
      {
        "name": "2f136a179c11a8d6c096",
        "ordinal": 0,
        "field": {
          "Column": {
            "Expression": {
              "SourceRef": {
                "Entity": "Argus SR"
              }
            },
            "Property": "SR Type"
          }
        },
        "type": "Categorical",
        "filter": {
          "Version": 2,
          "From": [
            {
              "Name": "a",
              "Entity": "Argus SR",
              "Type": 0
            }
          ],
          "Where": [
            {
              "Condition": {
                "In": {
                  "Expressions": [
                    {
                      "Column": {
                        "Expression": {
                          "SourceRef": {
                            "Source": "a"
                          }
                        },
                        "Property": "SR Type"
                      }
                    }
                  ],
                  "Values": [
                    [
                      {
                        "Literal": {
                          "Value": "'Service'"
                        }
                      }
                    ]
                  ]
                }
              }
            }
          ]
        },
        "howCreated": "User",
        "isHiddenInViewMode": true,
        "isLockedInViewMode": true
      },
      {
        "name": "2c42a4ef8cdc50c95915",
        "ordinal": 1,
        "field": {
          "Column": {
            "Expression": {
              "SourceRef": {
                "Entity": "Argus SR"
              }
            },
            "Property": "Range"
          }
        },
        "type": "Categorical",
        "filter": {
          "Version": 2,
          "From": [
            {
              "Name": "a",
              "Entity": "Argus SR",
              "Type": 0
            }
          ],
          "Where": [
            {
              "Condition": {
                "In": {
                  "Expressions": [
                    {
                      "Column": {
                        "Expression": {
                          "SourceRef": {
                            "Source": "a"
                          }
                        },
                        "Property": "Range"
                      }
                    }
                  ],
                  "Values": [
                    [
                      {
                        "Literal": {
                          "Value": "'HD'"
                        }
                      }
                    ],
                    [
                      {
                        "Literal": {
                          "Value": "'MD'"
                        }
                      }
                    ]
                  ]
                }
              }
            }
          ]
        },
        "howCreated": "User",
        "isHiddenInViewMode": true,
        "isLockedInViewMode": true
      },
      {
        "name": "d80d213b79a8bb765e0d",
        "ordinal": 2,
        "field": {
          "Column": {
            "Expression": {
              "SourceRef": {
                "Entity": "Argus SR"
              }
            },
            "Property": "Vehicle Type"
          }
        },
        "type": "Categorical",
        "filter": {
          "Version": 2,
          "From": [
            {
              "Name": "a",
              "Entity": "Argus SR",
              "Type": 0
            }
          ],
          "Where": [
            {
              "Condition": {
                "In": {
                  "Expressions": [
                    {
                      "Column": {
                        "Expression": {
                          "SourceRef": {
                            "Source": "a"
                          }
                        },
                        "Property": "Vehicle Type"
                      }
                    }
                  ],
                  "Values": [
                    [
                      {
                        "Literal": {
                          "Value": "'BEV'"
                        }
                      }
                    ]
                  ]
                }
              }
            }
          ]
        },
        "howCreated": "User",
        "isHiddenInViewMode": true,
        "isLockedInViewMode": true
      },
      {
        "name": "14e162cc62d78230460b",
        "ordinal": 3,
        "field": {
          "Column": {
            "Expression": {
              "SourceRef": {
                "Entity": "Argus SR"
              }
            },
            "Property": "Brand"
          }
        },
        "type": "Categorical",
        "filter": {
          "Version": 2,
          "From": [
            {
              "Name": "a",
              "Entity": "Argus SR",
              "Type": 0
            }
          ],
          "Where": [
            {
              "Condition": {
                "In": {
                  "Expressions": [
                    {
                      "Column": {
                        "Expression": {
                          "SourceRef": {
                            "Source": "a"
                          }
                        },
                        "Property": "Brand"
                      }
                    }
                  ],
                  "Values": [
                    [
                      {
                        "Literal": {
                          "Value": "'RT'"
                        }
                      }
                    ]
                  ]
                }
              }
            }
          ]
        },
        "howCreated": "User",
        "isHiddenInViewMode": true,
        "isLockedInViewMode": true
      },
      {
        "name": "502dd59e84e90df9d789",
        "ordinal": 4,
        "field": {
          "Measure": {
            "Expression": {
              "SourceRef": {
                "Entity": "KPI"
              }
            },
            "Property": "KPI+TXT Nb SR"
          }
        },
        "type": "Advanced"
      }
    ],
    "filterSortOrder": "Custom"
  }
}