{
  "$schema": "https://developer.microsoft.com/json-schemas/fabric/item/report/definition/visualContainer/2.3.0/schema.json",
  "name": "0fdbea82ff6dc8713b5c",
  "position": {
    "x": 316.98881961284837,
    "y": 59.635956152791522,
    "z": 750,
    "height": 29.630684713615238,
    "width": 109.78642014663684,
    "tabOrder": 1000
  },
  "visual": {
    "visualType": "card",
    "query": {
      "queryState": {
        "Values": {
          "projections": [
            {
              "field": {
                "Measure": {
                  "Expression": {
                    "SourceRef": {
                      "Entity": "KPI"
                    }
                  },
                  "Property": "KPI+TXT Nb SR short term evol"
                }
              },
              "queryRef": "KPI.KPI+TXT Nb SR short term evol",
              "nativeQueryRef": "KPI+TXT Nb SR short term evol"
            }
          ]
        }
      },
      "sortDefinition": {
        "isDefaultSort": true
      }
    },
    "objects": {
      "labels": [
        {
          "properties": {
            "fontSize": {
              "expr": {
                "Literal": {
                  "Value": "14D"
                }
              }
            },
            "color": {
              "solid": {
                "color": {
                  "expr": {
                    "Conditional": {
                      "Cases": [
                        {
                          "Condition": {
                            "Comparison": {
                              "ComparisonKind": 4,
                              "Left": {
                                "Measure": {
                                  "Expression": {
                                    "SourceRef": {
                                      "Entity": "KPI"
                                    }
                                  },
                                  "Property": "% SR short term evolution"
                                }
                              },
                              "Right": {
                                "Literal": {
                                  "Value": "0D"
                                }
                              }
                            }
                          },
                          "Value": {
                            "Literal": {
                              "Value": "'#6b943b'"
                            }
                          }
                        },
                        {
                          "Condition": {
                            "Comparison": {
                              "ComparisonKind": 2,
                              "Left": {
                                "Measure": {
                                  "Expression": {
                                    "SourceRef": {
                                      "Entity": "KPI"
                                    }
                                  },
                                  "Property": "% SR short term evolution"
                                }
                              },
                              "Right": {
                                "Literal": {
                                  "Value": "0D"
                                }
                              }
                            }
                          },
                          "Value": {
                            "Literal": {
                              "Value": "'#C62336'"
                            }
                          }
                        }
                      ]
                    }
                  }
                }
              }
            }
          }
        }
      ],
      "categoryLabels": [
        {
          "properties": {
            "show": {
              "expr": {
                "Literal": {
                  "Value": "false"
                }
              }
            }
          }
        }
      ]
    },
    "visualContainerObjects": {
      "title": [
        {
          "properties": {
            "titleWrap": {
              "expr": {
                "Literal": {
                  "Value": "true"
                }
              }
            },
            "text": {
              "expr": {
                "Literal": {
                  "Value": "'KPI % SR MHDV Service BEV'"
                }
              }
            }
          }
        }
      ],
      "background": [
        {
          "properties": {
            "show": {
              "expr": {
                "Literal": {
                  "Value": "false"
                }
              }
            },
            "transparency": {
              "expr": {
                "Literal": {
                  "Value": "0D"
                }
              }
            }
          }
        }
      ],
      "border": [
        {
          "properties": {
            "show": {
              "expr": {
                "Literal": {
                  "Value": "false"
                }
              }
            }
          }
        }
      ],
      "dropShadow": [
        {
          "properties": {
            "show": {
              "expr": {
                "Literal": {
                  "Value": "false"
                }
              }
            },
            "color": {
              "solid": {
                "color": {
                  "expr": {
                    "Literal": {
                      "Value": "'#D9CC3C'"
                    }
                  }
                }
              }
            }
          }
        }
      ],
      "visualTooltip": [
        {
          "properties": {
            "background": {
              "solid": {
                "color": {
                  "expr": {
                    "Literal": {
                      "Value": "'#4A4343'"
                    }
                  }
                }
              }
            }
          }
        }
      ],
      "visualHeader": [
        {
          "properties": {
            "show": {
              "expr": {
                "Literal": {
                  "Value": "false"
                }
              }
            },
            "foreground": {
              "solid": {
                "color": {
                  "expr": {
                    "Literal": {
                      "Value": "'#4A4343'"
                    }
                  }
                }
              }
            }
          }
        }
      ],
      "visualHeaderTooltip": [
        {
          "properties": {
            "background": {
              "solid": {
                "color": {
                  "expr": {
                    "Literal": {
                      "Value": "'#4A4343'"
                    }
                  }
                }
              }
            }
          }
        }
      ]
    },
    "drillFilterOtherVisuals": true
  },
  "parentGroupName": "6c39ba2db4536d6c2831",
  "filterConfig": {
    "filters": [
      {
        "name": "dde7d5a102b5ebedc070",
        "ordinal": 0,
        "field": {
          "Measure": {
            "Expression": {
              "SourceRef": {
                "Entity": "KPI"
              }
            },
            "Property": "KPI+TXT Nb SR short term evol"
          }
        },
        "type": "Advanced"
      },
      {
        "name": "d7b847ff848bc73eda5f",
        "ordinal": 1,
        "field": {
          "Column": {
            "Expression": {
              "SourceRef": {
                "Entity": "Argus SR"
              }
            },
            "Property": "Range"
          }
        },
        "type": "Categorical",
        "filter": {
          "Version": 2,
          "From": [
            {
              "Name": "a",
              "Entity": "Argus SR",
              "Type": 0
            }
          ],
          "Where": [
            {
              "Condition": {
                "In": {
                  "Expressions": [
                    {
                      "Column": {
                        "Expression": {
                          "SourceRef": {
                            "Source": "a"
                          }
                        },
                        "Property": "Range"
                      }
                    }
                  ],
                  "Values": [
                    [
                      {
                        "Literal": {
                          "Value": "'HD'"
                        }
                      }
                    ],
                    [
                      {
                        "Literal": {
                          "Value": "'MD'"
                        }
                      }
                    ]
                  ]
                }
              }
            }
          ]
        },
        "howCreated": "User",
        "isLockedInViewMode": true
      },
      {
        "name": "987e836a3275cac27e9d",
        "ordinal": 2,
        "field": {
          "Column": {
            "Expression": {
              "SourceRef": {
                "Entity": "Argus SR"
              }
            },
            "Property": "SR Type"
          }
        },
        "type": "Categorical",
        "filter": {
          "Version": 2,
          "From": [
            {
              "Name": "a",
              "Entity": "Argus SR",
              "Type": 0
            }
          ],
          "Where": [
            {
              "Condition": {
                "In": {
                  "Expressions": [
                    {
                      "Column": {
                        "Expression": {
                          "SourceRef": {
                            "Source": "a"
                          }
                        },
                        "Property": "SR Type"
                      }
                    }
                  ],
                  "Values": [
                    [
                      {
                        "Literal": {
                          "Value": "'Service'"
                        }
                      }
                    ]
                  ]
                }
              }
            }
          ]
        },
        "howCreated": "User",
        "isHiddenInViewMode": true,
        "isLockedInViewMode": true
      },
      {
        "name": "4b3cd1ecbc018ceb6a40",
        "ordinal": 3,
        "field": {
          "Column": {
            "Expression": {
              "SourceRef": {
                "Entity": "Argus SR"
              }
            },
            "Property": "Brand"
          }
        },
        "type": "Categorical",
        "filter": {
          "Version": 2,
          "From": [
            {
              "Name": "a",
              "Entity": "Argus SR",
              "Type": 0
            }
          ],
          "Where": [
            {
              "Condition": {
                "In": {
                  "Expressions": [
                    {
                      "Column": {
                        "Expression": {
                          "SourceRef": {
                            "Source": "a"
                          }
                        },
                        "Property": "Brand"
                      }
                    }
                  ],
                  "Values": [
                    [
                      {
                        "Literal": {
                          "Value": "'RT'"
                        }
                      }
                    ]
                  ]
                }
              }
            }
          ]
        },
        "howCreated": "User",
        "isHiddenInViewMode": true,
        "isLockedInViewMode": true
      },
      {
        "name": "f66db7df8bcac0b96db3",
        "ordinal": 4,
        "field": {
          "Column": {
            "Expression": {
              "SourceRef": {
                "Entity": "Argus SR"
              }
            },
            "Property": "Vehicle Type"
          }
        },
        "type": "Categorical",
        "filter": {
          "Version": 2,
          "From": [
            {
              "Name": "a",
              "Entity": "Argus SR",
              "Type": 0
            }
          ],
          "Where": [
            {
              "Condition": {
                "In": {
                  "Expressions": [
                    {
                      "Column": {
                        "Expression": {
                          "SourceRef": {
                            "Source": "a"
                          }
                        },
                        "Property": "Vehicle Type"
                      }
                    }
                  ],
                  "Values": [
                    [
                      {
                        "Literal": {
                          "Value": "'BEV'"
                        }
                      }
                    ]
                  ]
                }
              }
            }
          ]
        },
        "howCreated": "User",
        "isHiddenInViewMode": true,
        "isLockedInViewMode": true
      }
    ],
    "filterSortOrder": "Custom"
  }
}